subtitle_normalizer/__init__.py
subtitle_normalizer/conversor.py
subtitle_normalizer/normalizer.py
test/__init__.py
test/test_subtitle_normalizer.py
subtitle_normalizer-0.0.7.dist-info/LICENSE
subtitle_normalizer-0.0.7.dist-info/METADATA
subtitle_normalizer-0.0.7.dist-info/WHEEL
subtitle_normalizer-0.0.7.dist-info/top_level.txt
subtitle_normalizer-0.0.7.dist-info/RECORD
