Metadata-Version: 2.1
Name: subtitle-normalizer
Version: 0.0.7
Summary: Some tools to reformat SubRipFiles
Home-page: https://gitlab.com/Serbaf/subtitle_normalizer
Author: Sergio Puche García
Author-email: spuche@upv.es
License: GPL3
License-File: LICENSE
Requires-Dist: pysrt
